zerobouncesdk/__init__.py
zerobouncesdk/_zb_response.py
zerobouncesdk/_zb_utils.py
zerobouncesdk/zb_api_url.py
zerobouncesdk/zb_confidence.py
zerobouncesdk/zb_delete_file_response.py
zerobouncesdk/zb_exceptions.py
zerobouncesdk/zb_file_status_response.py
zerobouncesdk/zb_find_domain_response.py
zerobouncesdk/zb_find_email_format_response.py
zerobouncesdk/zb_get_activity_response.py
zerobouncesdk/zb_get_api_usage_response.py
zerobouncesdk/zb_get_credits_response.py
zerobouncesdk/zb_get_file_response.py
zerobouncesdk/zb_guess_format_response.py
zerobouncesdk/zb_send_file_response.py
zerobouncesdk/zb_validate_batch_element.py
zerobouncesdk/zb_validate_batch_response.py
zerobouncesdk/zb_validate_response.py
zerobouncesdk/zb_validate_status.py
zerobouncesdk/zb_validate_sub_status.py
zerobouncesdk/zerobouncesdk.py
zerobouncesdk-2.0.2.dist-info/licenses/LICENSE.txt
zerobouncesdk-2.0.2.dist-info/METADATA
zerobouncesdk-2.0.2.dist-info/WHEEL
zerobouncesdk-2.0.2.dist-info/top_level.txt
zerobouncesdk-2.0.2.dist-info/RECORD
