Metadata-Version: 2.4
Name: zerobouncesdk
Version: 2.0.2
Summary: ZeroBounce Python API - https://www.zerobounce.net.
Author-email: ZeroBounce <support@zerobounce.net>
Project-URL: Homepage, https://github.com/zerobounce/zero-bounce-python-sdk-setup
Keywords: zero,bounce,sdk
Classifier: Intended Audience :: Developers
Classifier: License :: OSI Approved :: MIT License
Classifier: Operating System :: OS Independent
Classifier: Programming Language :: Python
Classifier: Programming Language :: Python :: 3
Requires-Python: >=3.7
License-File: LICENSE.txt
Requires-Dist: requests>=2.22.0
Dynamic: license-file
